{
    "李高柏": [
      ["巴府山", "雇佣人 of x, 对方 of x"], 
      ["鬼印", "朋友 of x, 邻居 of x"], 
      ["如娅", "朋友 of x, 邻居 of x"], 
      ["隼", "学生 of x, 帮手 of x"], 
      ["甘玛", "朋友 of x, 怀疑 of x"]
    ],
    "巴府山": [
      ["李高柏", "雇佣人 of x, 对方 of x"], 
      ["鬼印", "朋友 of x, 邻居 of x"], 
      ["如娅", "朋友 of x, 邻居 of x"], 
      ["隼", "儿子 of x, 学生 of x"], 
      ["甘玛", "妹妹 of x, 朋友 of x"]
    ],
    "鬼印": [
      ["李高柏", "朋友 of x, 邻居 of x"], 
      ["巴府山", "朋友 of x, 邻居 of x"], 
      ["如娅", "朋友 of x, 邻居 of x"], 
      ["隼", "学生 of x, 帮手 of x"], 
      ["甘玛", "妹妹 of x, 朋友 of x"]
    ],
    "如娅": [
      ["李高柏", "朋友 of x, 邻居 of x"], 
      ["巴府山", "朋友 of x, 邻居 of x"], 
      ["鬼印", "朋友 of x, 邻居 of x"], 
      ["隼", "学生 of x, 帮手 of x"], 
      ["甘玛", "朋友 of x, 怀疑 of x"]
    ],
    "隼": [
      ["李高柏", "学生 of x, 帮手 of x"], 
      ["巴府山", "儿子 of x, 学生 of x"], 
      ["鬼印", "学生 of x, 帮手 of x"], 
      ["如娅", "学生 of x, 帮手 of x"], 
      ["甘玛", "学生 of x, 怀疑 of x"]
    ],
    "甘玛": [
      ["李高柏", "朋友 of x, 怀疑 of x"], 
      ["巴府山", "妹妹 of x, 朋友 of x"], 
      ["鬼印", "妹妹 of x, 朋友 of x"], 
      ["如娅", "朋友 of x, 怀疑 of x"], 
      ["隼", "学生 of x, 怀疑 of x"]
    ],
    "李德木": [
      ["李高柏", "朋友 of x, 怀疑 of x"], 
      ["巴府山", "朋友 of x, 对方 of x"], 
      ["鬼印", "朋友 of x, 邻居 of x"], 
      ["如娅", "朋友 of x, 邻居 of x"], 
      ["隼", "学生 of x, 帮手 of x"]
    ]
}