{
    "收养的男孩": [
        [
            "方叶",
            "兄弟",
            "哥哥",
            "同学",
            "朋友"
        ],
        [
            "方眠",
            "兄弟",
            "哥哥",
            "Familiar stranger",
            "Childhood friend",
            "旧友"
        ],
        [
            "方竹",
            "brothers",
            "childhood friends",
            "confidants",
            "partners in crime",
            "mentor and mentee",
            "benefactor and beneficiary",
            "allies",
            "friends with benefits"
        ],
        [
            "方絮",
            "brother",
            "弟弟",
            "姐姐",
            "妈妈"
        ],
        [
            "李延",
            "兄弟",
            "弟子",
            "养子",
            "朋友"
        ],
        [
            "李氏",
            "兄弟",
            "弟子",
            "养子",
            "亲友",
            "合作者"
        ],
        [
            "李钦仁",
            "兄弟",
            "弟子",
            "朋友",
            "同胞胎",
            "师傅"
        ],
        [
            "陈倩",
            "兄弟/姐妹",
            "敌人",
            "朋友",
            "Lehrer und Schüler",
            "Helfer"
        ]
    ],
    "方叶": [
        [
            "收养的男孩",
            "兄弟",
            "哥哥",
            "同学",
            "朋友"
        ],
        [
            "方眠",
            "brother/sister",
            "childhood sweethearts"
        ],
        [
            "方竹",
            "older brother",
            "close relationship",
            "protective",
            "admiration"
        ],
        [
            "方絮",
            "brother/sister",
            "childhood sweethearts"
        ],
        [
            "李延",
            "brother-in-law, husband of sister"
        ],
        [
            "李氏",
            "同人",
            "兄弟",
            "嫂子",
            "儿女",
            "丈夫"
        ],
        [
            "李钦仁",
            "relationship 1, relationship 2, relationship 3, relationship 4, relationship 5"
        ],
        [
            "陈倩",
            "同人",
            "好友",
            "姐弟",
            "潜在的敌人",
            "帮手",
            "信者",
            "受欢迎的人"
        ]
    ],
    "方眠": [
        [
            "收养的男孩",
            "兄弟",
            "哥哥",
            "Familiar stranger",
            "Childhood friend",
            "旧友"
        ],
        [
            "方叶",
            "brother/sister",
            "childhood sweethearts"
        ],
        [
            "方竹",
            "biological mother",
            "romantic relationship",
            "enemy"
        ],
        [
            "方絮",
            "brother/sister",
            "childhood sweethearts"
        ],
        [
            "李仲",
            "brother-in-law, husband of sister"
        ],
        [
            "李延",
            "brother-in-law, husband of sister"
        ],
        [
            "李氏",
            "同人",
            "哥哥",
            "嫂子",
            "儿媳",
            "外甥"
        ],
        [
            "李钦仁",
            "biological mother",
            "former lover"
        ],
        [
            "陈倩",
            "brother/sister",
            "childhood sweethearts"
        ]
    ],
    "方竹": [
        [
            "收养的男孩",
            "brothers",
            "childhood friends",
            "confidants",
            "partners in crime",
            "mentor and mentee",
            "benefactor and beneficiary",
            "allies",
            "friends with benefits"
        ],
        [
            "方叶",
            "younger brother",
            "close relationship",
            "respect",
            "unaware"
        ],
        [
            "方眠",
            "adopted mother",
            "romantic relationship",
            "enemy"
        ],
        [
            "方絮",
            "李延",
            "李仲",
            "李王爷",
            "迷信"
        ],
        [
            "李仲",
            "biological father"
        ],
        [
            "李延",
            "father"
        ],
        [
            "李氏",
            "husband",
            "friend",
            "savior",
            "informant",
            "customer"
        ],
        [
            "李钦仁",
            "biological father",
            "acquaintance",
            "master-servant",
            "friend"
        ],
        [
            "chen qi",
            "Friend"
        ]
    ],
    "方絮": [
        [
            "收养的男孩",
            "brother",
            "弟弟",
            "姐姐",
            "妈妈"
        ],
        [
            "方叶",
            "brother/sister",
            "childhood sweethearts"
        ],
        [
            "方眠",
            "brother/sister",
            "childhood sweethearts"
        ],
        [
            "方竹",
            "李延",
            "李仲",
            "李王爷",
            "迷信"
        ],
        [
            "李仲",
            "brother-in-law",
            "erstwhile lover"
        ],
        [
            "李延",
            "brother-in-law, husband of sister"
        ],
        [
            "李氏",
            "同人",
            "哥哥/妹妹",
            "嫁人",
            "父母",
            "子女",
            "兄弟",
            "Friend"
        ],
        [
            "李钦仁",
            "relationship 1, relationship 2"
        ],
        [
            "陈倩",
            "同人",
            "好友",
            "潜在的爱情",
            "家庭成员",
            "敌人",
            "former 情人"
        ]
    ],
    "李延": [
        [
            "收养的男孩",
            "兄弟",
            "弟子",
            "养子",
            "舅舅"
        ],
        [
            "方叶",
            "brother-in-law, husband of sister"
        ],
        [
            "方眠",
            "sister-in-law, wife of brother"
        ],
        [
            "方竹",
            "son"
        ],
        [
            "方絮",
            "sister-in-law, wife of brother"
        ],
        [
            "李仲",
            "brother, twin brother"
        ],
        [
            "李氏",
            "兄弟",
            "嫂嫂",
            "父亲",
            "儿子",
            "家人"
        ],
        [
            "李钦仁",
            " Husband of X",
            " Father of X"
        ],
        [
            "陈倩",
            "Child of X",
            "Sibling of X",
            "Relative of X",
            "Nephew of X",
            "Aunt of X",
            " Uncle of X",
            "Cousin of X"
        ]
    ],
    "李氏": [
        [
            "收养的男孩",
            "兄弟",
            "弟子",
            "养子",
            "亲友",
            "合作者"
        ],
        [
            "方叶",
            "同人",
            "兄弟",
            "嫂子",
            "儿女",
            "丈夫"
        ],
        [
            "方眠",
            "同人",
            "哥哥",
            "嫂子",
            "儿媳",
            "外甥"
        ],
        [
            "方竹",
            "husband",
            "friend",
            "savior",
            "informant",
            "customer"
        ],
        [
            "方絮",
            "同人",
            "哥哥/妹妹",
            "嫁人",
            "父母",
            "子女",
            "兄弟",
            "Friend"
        ],
        [
            "李仲",
            "朋友",
            "师徒",
            "Familiar",
            "爱情"
        ],
        [
            "李延",
            "兄弟",
            "嫂嫂",
            "父亲",
            "儿子",
            "家人"
        ],
        [
            "李钦仁",
            " Husband of X",
            " Father of X"
        ],
        [
            "陈倩",
            "恋人、兄弟、医生、朋友、家人"
        ]
    ],
    "李钦仁": [
        [
            "收养的男孩",
            "兄弟",
            "弟子",
            "朋友",
            "同胞胎",
            "师傅"
        ],
        [
            "方叶",
            "relationship 1, relationship 2, relationship 3, relationship 4, relationship 5"
        ],
        [
            "方眠",
            "father",
            "former lover"
        ],
        [
            "方竹",
            "husband of daughter",
            "acquaintance",
            "master",
            "friend"
        ],
        [
            "方絮",
            "relationship 1, relationship 2"
        ],
        [
            "李仲",
            "father",
            "master",
            "teacher",
            "friend"
        ],
        [
            "李延",
            "Wife of X",
            "Mother of X"
        ],
        [
            "李氏",
            " Husband of X",
            " Father of X"
        ]
    ],
    "陈倩": [
        [
            "收养的男孩",
            "兄弟/姐妹",
            "敌人",
            "朋友",
            "Lehrer und Schüler",
            "Helfer"
        ],
        [
            "方叶",
            "同人",
            "好友",
            "姐弟",
            "潜在的敌人",
            "帮手",
            "信者",
            "受欢迎的人"
        ],
        [
            "方眠",
            "brother/sister",
            "childhood sweethearts"
        ],
        [
            "method zhu",
            "Friend"
        ],
        [
            "方絮",
            " same person",
            "好友",
            "潜在的爱情",
            "家庭成员",
            "敌人",
            "former 情人"
        ],
        [
            "李仲",
            "Childhood sweethearts",
            "Siblings"
        ],
        [
            "李氏",
            "恋人、兄弟、医生、朋友、家人"
        ]
    ],
    "李仲": [
        [
            "方眠",
            "sister-in-law, wife of brother"
        ],
        [
            "方竹",
            "son"
        ],
        [
            "方絮",
            "sister-in-law",
            "erstwhile lover"
        ],
        [
            "李延",
            "brother, twin brother"
        ],
        [
            "李氏",
            "朋友",
            "师徒",
            "Familiar",
            "爱情"
        ],
        [
            "李钦仁",
            "son",
            "master-servant",
            "mentor-student",
            "friend"
        ],
        [
            "陈倩",
            "Childhood sweethearts",
            "Siblings"
        ]
    ],
    "chen jin": [
        [
            "李延",
            "Child of X",
            "Sibling of X",
            "Relative of X",
            "Nephew of X",
            "Aunt of X",
            "Uncle of X",
            "Cousin of X"
        ]
    ]
}