{
    "冯双骥": [
        [
            "冯竹",
            "family member, servant"
        ],
        [
            "尹少鸣",
            "relationship 1, relationship 2"
        ],
        [
            "赵万雷",
            "father-in-law",
            "husband of 赵万雷's daughter"
        ],
        [
            "赵卫",
            "saves her from a bind situation",
            "a person with unclear intentions",
            "helps her",
            "unsure of his intentions"
        ],
        [
            "齐岳",
            "父亲",
            "保护者"
        ]
    ],
    "冯竹": [
        [
            "冯双骥",
            "family member, master"
        ],
        [
            "尹少鸣",
            "perpetrator of X",
            "bully of X"
        ],
        [
            "赵万雷",
            "loyal servant and helper",
            "close friend and confidant",
            "potential love interest or romantic partner",
            "savior or rescuer",
            "rival or competitor"
        ],
        [
            "赵卫",
            "relationship 1",
            "relationship 2"
        ],
        [
            "赵洛意",
            "savior",
            "friend",
            "love interest"
        ],
        [
            "赵秋儿",
            "perpetrator of X",
            "bully of X"
        ],
        [
            "齐岳",
            "acquaintance",
            "helper"
        ]
    ],
    "尹少鸣": [
        [
            "冯双骥",
            "relationship 1, relationship 2"
        ],
        [
            "冯竹",
            "victim of X",
            "suspect of X"
        ],
        [
            "赵万雷",
            "captor, savior, and informant"
        ],
        [
            "赵卫",
            "stranger, friend, savior, manipulator, helper, betrayer, suspect, victim, witness, nemesis"
        ],
        [
            "赵洛意",
            "friend, savior, confidant, stranger, suspect"
        ],
        [
            "赵秋儿",
            "savior",
            "friend"
        ],
        [
            "齐岳",
            "subordinate",
            "assistant",
            "friend",
            "acquaintance",
            "classmate",
            "schoolmate",
            "neighbor",
            "helper",
            "informant",
            "victim"
        ]
    ],
    "赵万雷": [
        [
            "冯双骥",
            "father-in-law",
            "husband of 赵万雷's daughter"
        ],
        [
            "冯竹",
            "loyal servant and helper",
            "close friend and confidant",
            "potential love interest or romantic partner",
            "savior or rescuer",
            "rival or competitor"
        ],
        [
            "尹少鸣",
            "captive, saved person, and informant"
        ],
        [
            "赵卫",
            "father-daughter relationship",
            "husband-wife relationship",
            "master-servant relationship",
            "employer-employee relationship",
            "mentor-apprentice relationship",
            "friend-friend relationship"
        ],
        [
            "赵洛意",
            "father-daughter",
            "master-servant",
            "rescuer-rescued",
            "travel companion-traveler",
            "friend-friend"
        ],
        [
            "赵秋儿",
            "father-daughter relationship"
        ]
    ],
    "赵卫": [
        [
            "冯双骥",
            "helped by him",
            "unsure of his intentions",
            "saved by him",
            "has complicated feelings towards him"
        ],
        [
            "冯竹",
            "relationship 1",
            "relationship 2"
        ],
        [
            "尹少鸣",
            "stranger, friend, savior, manipulator, helper, betrayer, suspect, victim, witness, nemesis"
        ],
        [
            "赵万雷",
            "father-daughter relationship",
            "husband-wife relationship",
            "master-servant relationship",
            "employer-employee relationship",
            "mentor-apprentice relationship",
            "friend-friend relationship"
        ],
        [
            "赵秋儿",
            "father",
            "mother",
            "older brother",
            "younger brother",
            "uncle",
            "aunt",
            "cousin",
            "friend",
            "mentor",
            "student",
            "employer",
            "subordinate",
            "colleague",
            "business partner",
            "customer"
        ],
        [
            "齐岳",
            "relationship 1, relationship 2, ..., relationship 10"
        ]
    ],
    "冯double骥": [
        [
            "赵秋儿",
            "husband of X",
            "Perpetrator of X"
        ]
    ],
    "赵秋儿": [
        [
            "冯双骥",
            "wife of X",
            "Victim of X"
        ],
        [
            "冯竹",
            "victim of X",
            "suspect of X"
        ],
        [
            "尹少鸣",
            "savior",
            "friend"
        ],
        [
            "赵万雷",
            "daughter-father relationship"
        ],
        [
            "赵卫",
            "father",
            "mother",
            "older brother",
            "younger brother",
            "uncle",
            "aunt",
            "cousin",
            "friend",
            "mentor",
            "student",
            "employer",
            "subordinate",
            "colleague",
            "business partner",
            "customer"
        ],
        [
            "赵洛意",
            "friend"
        ],
        [
            "齐岳",
            "saves her from a bind, acquaintance"
        ]
    ],
    "齐岳": [
        [
            "冯双骥",
            "儿子",
            "被保护人"
        ],
        [
            "冯竹",
            "acquaintance",
            "helped by"
        ],
        [
            "尹少鸣",
            "subordinate",
            "assistant",
            "friend",
            "acquaintance",
            "classmate",
            "schoolmate",
            "neighbor",
            "helper",
            "informant",
            "victim"
        ],
        [
            "赵卫",
            "relationship 1, relationship 2, ..., relationship 10"
        ],
        [
            "赵洛意",
            "father's employee",
            "acquaintance",
            "colleague",
            "friend",
            "classmate"
        ],
        [
            "赵秋儿",
            "saves her from a bind, acquaintance"
        ]
    ],
    "赵洛意": [
        [
            "冯竹",
            "savior",
            "friend",
            "love interest"
        ],
        [
            "尹少鸣",
            "friend, savior, confidant, stranger, suspect"
        ],
        [
            "赵万雷",
            "father-daughter",
            "master-servant",
            "rescuer-rescued",
            "travel companion-traveler",
            "friend-friend"
        ],
        [
            "赵秋儿",
            "friend"
        ],
        [
            "齐岳",
            "father's employee",
            "acquaintance",
            "colleague",
            "friend",
            "classmate"
        ]
    ]
}