{
    "Dr. Paloski": [
      ["Yilin Carter", "strict of x, authoritative of x, mentor of x"], 
      ["Hans Rymorite", "colleague of x, deceased of x"]
    ],
    "Hans Rymorite": [
      ["Yilin Carter", "colleague of x, deceased of x"], 
      ["Drake Rimerite", "twin brother of x, colleague of x"]
    ],
    "Drake Rimerite": [
      ["Yilin Carter", "colleague of x, friendly of x"], 
      ["Hans Rymorite", "twin brother of x, colleague of x"]
    ],
    "Head Nurse Costa": [
      ["Yilin Carter", "friendly of x, helpful of x"], 
      ["Dr. Paloski", "colleague of x, respectful of x"]
    ],
    "Hospital Dean Berkeley": [
      ["Yilin Carter", "acquaintance of x, supervisor of x"], 
      ["Dr. Paloski", "colleague of x, respectful of x"]
    ],
    "Father Tom": [
      ["Yilin Carter", "acquaintance of x"], 
      ["Drake Rimerite", "friend of x"]
    ],
    "Gallimerret": [
      ["Yilin Carter", "acquaintance of x"], 
      ["Hans Rymorite", "wife of x"]
    ],
    "Jim Mason": [
      ["Yilin Carter", "acquaintance of x"], 
      ["Head Nurse Costa", "patient of x, lawsuit of x"]
    ],
    "Eric": [
      ["Yilin Carter", "acquaintance of x"], 
      ["Dr. Drake", "patient of x, saved of x"]
    ]
}