{
    "Hei Li": [
      ["Qi Qingli", "adoptive father of x, mentor of x"], 
      ["Qi Gu Fei", "adoptive brother of x"], 
      ["Mrs. Ruan", "wife of x, friend of x"], 
      ["Zhaonan", "sibling of x, friend of x"], 
      ["Wangdi", "rival of x"], 
      ["Guilang", "adoptive brother of x, rival of x"], 
      ["Luo Xiucai", "friend of x, rival of x"], 
      ["Luo Younuo", "friend of x, rival of x"], 
      ["Xue Yan", "sibling of x, rival of x"], 
      ["Guilang", "adoptive brother of x, rival of x"], 
      ["Zhaonan", "sibling of x, friend of x"], 
      ["Wang Zimo", "adoptive brother of x, friend of x"]
    ],
    "Qi Qingli": [
      ["Hei Li", "adoptive son of x"], 
      ["Qi Gu Fei", "adoptive father of x, adoptive brother of x"], 
      ["Mrs. Ruan", "adoptive father of x, landlord of x"], 
      ["Zhaonan", "adoptive father of x, adoptive brother of x"], 
      ["Wangdi", "adoptive father of x, adoptive brother of x"], 
      ["Guilang", "adoptive father of x, mentor of x"], 
      ["Luo Xiucai", "adoptive father of x, rival of x"], 
      ["Luo Younuo", "acquaintance of x"], 
      ["Xue Yan", "adoptive father of x, adoptive brother of x"], 
      ["Guilang", "adoptive father of x, mentor of x"], 
      ["Zhaonan", "adoptive father of x, adoptive brother of x"], 
      ["Wang Zimo", "student of x"]
    ],
    "Qi Gu Fei": [
      ["Hei Li", "adoptive brother of x"], 
      ["Qi Qingli", "adoptive father of x, adoptive brother of x"], 
      ["Mrs. Ruan", "adoptive brother of x, student of x"], 
      ["Zhaonan", "adoptive brother of x"], 
      ["Wangdi", "adoptive brother of x, rival of x"], 
      ["Guilang", "adoptive brother of x, rival of x"], 
      ["Luo Xiucai", "same person as x (different reference), same person as x (different identity)"], 
      ["Luo Younuo", "sibling of x, friend of x"], 
      ["Xue Yan", "adoptive brother of x, rival of x"], 
      ["Guilang", "adoptive brother of x, rival of x"], 
      ["Zhaonan", "adoptive brother of x"], 
      ["Wang Zimo", "adoptive brother of x"]
    ],
    "Mrs. Ruan": [
      ["Hei Li", "husband of x, friend of x"], 
      ["Qi Qingli", "landlord of x, adoptive father of x"], 
      ["Qi Gu Fei", "landlord of x, teacher of x"], 
      ["Zhaonan", "landlord of x"], 
      ["Wangdi", "landlord of x"], 
      ["Guilang", "landlord of x, mother of x"], 
      ["Luo Xiucai", "employee of x"], 
      ["Xue Yan", "landlord of x, adoptive mother of x"], 
      ["Guilang", "landlord of x, mother of x"], 
      ["Zhaonan", "landlord of x"], 
      ["Wang Zimo", "landlord of x, mother in law of x"]
    ],
    "Zhaonan": [
      ["Hei Li", "sibling of x, friend of x"], 
      ["Hei Li", "sibling of x, friend of x"], 
      ["Qi Qingli", "adoptive father of x, adoptive brother of x"], 
      ["Qi Qingli", "adoptive father of x, adoptive brother of x"], 
      ["Qi Gu Fei", "adoptive sister of x"], 
      ["Qi Gu Fei", "adoptive sister of x"], 
      ["Mrs. Ruan", "mentor of x"], 
      ["Mrs. Ruan", "mentor of x"], 
      ["Wangdi", "sister of x, rival of x"], 
      ["Guilang", "sibling of x, rival of x"], 
      ["Luo Xiucai", "wife of x, romantic relationships with x"], 
      ["Luo Younuo", "friend of x, rival of x"], 
      ["Xue Yan", "friend of x, rival of x"], 
      ["Guilang", "sibling of x, rival of x"], 
      ["Zhaonan", "rival of x, enemy of x"], 
      ["Wang Zimo", "same person as x (different reference), same person as x (different identity)"], 
      ["Wangdi", "sister of x, rival of x"], 
      ["Guilang", "sibling of x, rival of x"], 
      ["Luo Xiucai", "acquaintance of x, neighbour of x"], 
      ["Luo Younuo", "friend of x"], 
      ["Xue Yan", "sister of x, rival of x"], 
      ["Guilang", "sibling of x, rival of x"], 
      ["Wang Zimo", "same person as x (different reference), same person as x (different identity)"]
    ],
    "Wangdi": [
      ["Hei Li", "rival of x"], 
      ["Qi Qingli", "adoptive father of x, adoptive brother of x"], 
      ["Qi Gu Fei", "adoptive sister of x, rival of x"], 
      ["Mrs. Ruan", "sister of x, daughter of x"], 
      ["Zhaonan", "sister of x, rival of x"], 
      ["Guilang", "sister of x, friend of x"], 
      ["Luo Xiucai", "friend of x"], 
      ["Luo Younuo", "sibling of x"], 
      ["Xue Yan", "sister of x, friend of x"], 
      ["Guilang", "sister of x, friend of x"], 
      ["Zhaonan", "sister of x, rival of x"], 
      ["Wang Zimo", "sister of x, rival of x, sister of x, rival of x"]
    ],
    "Guilang": [
      ["Hei Li", "adoptive brother of x, rival of x"], 
      ["Hei Li", "adoptive brother of x, rival of x"], 
      ["Qi Qingli", "adoptive son of x"], 
      ["Qi Qingli", "adoptive son of x"], 
      ["Qi Gu Fei", "adoptive brother of x, rival of x"], 
      ["Qi Gu Fei", "adoptive brother of x, rival of x"], 
      ["Mrs. Ruan", "son of x, brother of x"], 
      ["Mrs. Ruan", "son of x, brother of x"], 
      ["Zhaonan", "sibling of x, rival of x"], 
      ["Zhaonan", "sibling of x, rival of x"], 
      ["Wangdi", "sister of x, friend of x"], 
      ["Wangdi", "sister of x, friend of x"], 
      ["Luo Xiucai", "friend of x"], 
      ["Luo Younuo", "brother of x, friend of x"], 
      ["Guilang", "sibling of x, child of x, son of x"], 
      ["Zhaonan", "sibling of x, rival of x"], 
      ["Wang Zimo", "sibling of x, friend of x"], 
      ["Luo Xiucai", "student of x, informant of x"], 
      ["Luo Younuo", "adoptive brother of x, rival of x"], 
      ["Xue Yan", "sibling of x, rival of x"], 
      ["Zhaonan", "sibling of x, rival of x"], 
      ["Wang Zimo", "sibling of x, friend of x"]
    ],
    "Luo Xiucai": [
      ["Hei Li", "friend of x, rival of x"], 
      ["Qi Qingli", "rival of x, acquaintance of x"], 
      ["Qi Gu Fei", "same person as x (different reference), same person as x (different identity)"], 
      ["Mrs. Ruan", "employee of x"], 
      ["Zhaonan", "husband of x, romantic relationships with x"], 
      ["Wangdi", "friend of x"], 
      ["Guilang", "teacher of x"], 
      ["Luo Younuo", "father of x"], 
      ["Xue Yan", "father of x"], 
      ["Guilang", "teacher of x, informant of x"], 
      ["Zhaonan", "acquaintance of x, neighbour of x"], 
      ["Wang Zimo", "same person as x (different reference), same person as x (different identity)"]
    ],
    "Luo Younuo": [
      ["Hei Li", "friend of x, rival of x"], 
      ["Qi Qingli", "acquaintance of x"], 
      ["Qi Gu Fei", "sibling of x, friend of x"], 
      ["Zhaonan", "friend of x, rival of x"], 
      ["Wangdi", "sibling of x"], 
      ["Guilang", "brother of x, friend of x"], 
      ["Luo Xiucai", "son of x"], 
      ["Xue Yan", "sibling of x"], 
      ["Guilang", "adoptive brother of x, rival of x"], 
      ["Zhaonan", "friend of x"], 
      ["Wang Zimo", "adoptive brother of x, rival of x"]
    ],
    "Xue Yan": [
      ["Hei Li", "sibling of x, rival of x"], 
      ["Qi Qingli", "adoptive father of x, adoptive brother of x"], 
      ["Qi Gu Fei", "adoptive sister of x, rival of x"], 
      ["Mrs. Ruan", "daughter of x, student of x"], 
      ["Zhaonan", "friend of x, rival of x"], 
      ["Wangdi", "sister of x, friend of x"], 
      ["Luo Xiucai", "son of x, student of x"], 
      ["Luo Younuo", "sibling of x"], 
      ["Guilang", "sibling of x, rival of x"], 
      ["Zhaonan", "sister of x, rival of x"], 
      ["Wang Zimo", "sister of x, rival of x"]
    ],
    "Wang Zimo": [
      ["Hei Li", "adoptive brother of x, friend of x"], 
      ["Qi Qingli", "teacher of x"], 
      ["Qi Gu Fei", "adoptive brother of x"], 
      ["Mrs. Ruan", "tenant of x, son in law of x"], 
      ["Zhaonan", "husband of x, fiance of x"], 
      ["Wangdi", "sister of x, rival of x, sister of x, rival of x"], 
      ["Guilang", "sibling of x, friend of x"], 
      ["Luo Xiucai", "same person as x (different reference), same person as x (different identity)"], 
      ["Luo Younuo", "adoptive brother of x, rival of x"], 
      ["Xue Yan", "sister of x, rival of x"], 
      ["Guilang", "sibling of x, friend of x"], 
      ["Zhaonan", "husband of x, fiance of x"]
    ]
}